do2sshconfig.py
setup.py
digitalocean_to_sshconfig.egg-info/PKG-INFO
digitalocean_to_sshconfig.egg-info/SOURCES.txt
digitalocean_to_sshconfig.egg-info/dependency_links.txt
digitalocean_to_sshconfig.egg-info/entry_points.txt
digitalocean_to_sshconfig.egg-info/requires.txt
digitalocean_to_sshconfig.egg-info/top_level.txt