Metadata-Version: 1.1
Name: digitalocean-to-sshconfig
Version: 0.0.1
Summary: automatically add your droplets into your ssh config.
Home-page: https://github.com/emre/digitalocean_to_sshconfig
Author: Emre Yilmaz
Author-email: mail@emreyilmaz.me
License: MIT
Platform: UNKNOWN
Classifier: Development Status :: 3 - Alpha
Classifier: Intended Audience :: Developers
